[
  {
    "Name": "none",
    "Idx": 0,
    "Id": 0,
    "ZoneId": 61440,
    "ConvertedZoneNames": [],
    "ConvertedZoneType": ""
  },
  {
    "Name": "",
    "Idx": 6,
    "Id": 16994310,
    "ZoneId": 53,
    "ConvertedZoneNames": [],
    "ConvertedZoneType": ""
  },
  {
    "Name": "Moogle",
    "Idx": 8,
    "Id": 16994312,
    "ZoneId": 53,
    "ConvertedZoneNames": [],
    "ConvertedZoneType": ""
  },
  {
    "Name": "Moogle",
    "Idx": 9,
    "Id": 16994313,
    "ZoneId": 53,
    "ConvertedZoneNames": [],
    "ConvertedZoneType": ""
  },
  {
    "Name": "Moogle",
    "Idx": 10,
    "Id": 16994314,
    "ZoneId": 53,
    "ConvertedZoneNames": [],
    "ConvertedZoneType": ""
  },
  {
    "Name": "Moogle",
    "Idx": 11,
    "Id": 16994315,
    "ZoneId": 53,
    "ConvertedZoneNames": [],
    "ConvertedZoneType": ""
  },
  {
    "Name": "Moogle",
    "Idx": 12,
    "Id": 16994316,
    "ZoneId": 53,
    "ConvertedZoneNames": [],
    "ConvertedZoneType": ""
  },
  {
    "Name": "Moogle",
    "Idx": 13,
    "Id": 16994317,
    "ZoneId": 53,
    "ConvertedZoneNames": [],
    "ConvertedZoneType": ""
  },
  {
    "Name": "Moogle",
    "Idx": 14,
    "Id": 16994318,
    "ZoneId": 53,
    "ConvertedZoneNames": [],
    "ConvertedZoneType": ""
  },
  {
    "Name": "Moogle",
    "Idx": 15,
    "Id": 16994319,
    "ZoneId": 53,
    "ConvertedZoneNames": [],
    "ConvertedZoneType": ""
  },
  {
    "Name": "Abihaal",
    "Idx": 16,
    "Id": 16994320,
    "ZoneId": 53,
    "ConvertedZoneNames": [],
    "ConvertedZoneType": ""
  },
  {
    "Name": "Sajhra",
    "Idx": 17,
    "Id": 16994321,
    "ZoneId": 53,
    "ConvertedZoneNames": [],
    "ConvertedZoneType": ""
  },
  {
    "Name": "Bellowing Scout",
    "Idx": 18,
    "Id": 16994322,
    "ZoneId": 53,
    "ConvertedZoneNames": [],
    "ConvertedZoneType": ""
  },
  {
    "Name": "Belligerent Sheep",
    "Idx": 19,
    "Id": 16994323,
    "ZoneId": 53,
    "ConvertedZoneNames": [],
    "ConvertedZoneType": ""
  },
  {
    "Name": "Yohj Dukonlhy",
    "Idx": 20,
    "Id": 16994324,
    "ZoneId": 53,
    "ConvertedZoneNames": [],
    "ConvertedZoneType": ""
  },
  {
    "Name": "Teco Chatpaya",
    "Idx": 21,
    "Id": 16994325,
    "ZoneId": 53,
    "ConvertedZoneNames": [],
    "ConvertedZoneType": ""
  },
  {
    "Name": "Door_1h0",
    "Idx": 24,
    "Id": 16994328,
    "ZoneId": 53,
    "ConvertedZoneNames": [],
    "ConvertedZoneType": ""
  },
  {
    "Name": "Door_1h1",
    "Idx": 25,
    "Id": 16994329,
    "ZoneId": 53,
    "ConvertedZoneNames": [],
    "ConvertedZoneType": ""
  },
  {
    "Name": "Cam_1h2",
    "Idx": 26,
    "Id": 16994330,
    "ZoneId": 53,
    "ConvertedZoneNames": [],
    "ConvertedZoneType": ""
  },
  {
    "Name": "Cam_1h3",
    "Idx": 27,
    "Id": 16994331,
    "ZoneId": 53,
    "ConvertedZoneNames": [],
    "ConvertedZoneType": ""
  },
  {
    "Name": "Home Point #1",
    "Idx": 28,
    "Id": 16994332,
    "ZoneId": 53,
    "ConvertedZoneNames": [],
    "ConvertedZoneType": ""
  },
  {
    "Name": "Home Point #2",
    "Idx": 29,
    "Id": 16994333,
    "ZoneId": 53,
    "ConvertedZoneNames": [],
    "ConvertedZoneType": ""
  },
  {
    "Name": "Home Point #3",
    "Idx": 30,
    "Id": 16994334,
    "ZoneId": 53,
    "ConvertedZoneNames": [],
    "ConvertedZoneType": ""
  },
  {
    "Name": "Home Point #4",
    "Idx": 31,
    "Id": 16994335,
    "ZoneId": 53,
    "ConvertedZoneNames": [],
    "ConvertedZoneType": ""
  },
  {
    "Name": "Home Point #5",
    "Idx": 32,
    "Id": 16994336,
    "ZoneId": 53,
    "ConvertedZoneNames": [],
    "ConvertedZoneType": ""
  },
  {
    "Name": "",
    "Idx": 33,
    "Id": 16994337,
    "ZoneId": 53,
    "ConvertedZoneNames": [],
    "ConvertedZoneType": ""
  },
  {
    "Name": "",
    "Idx": 34,
    "Id": 16994338,
    "ZoneId": 53,
    "ConvertedZoneNames": [],
    "ConvertedZoneType": ""
  },
  {
    "Name": "",
    "Idx": 35,
    "Id": 16994339,
    "ZoneId": 53,
    "ConvertedZoneNames": [],
    "ConvertedZoneType": ""
  },
  {
    "Name": "",
    "Idx": 36,
    "Id": 16994340,
    "ZoneId": 53,
    "ConvertedZoneNames": [],
    "ConvertedZoneType": ""
  },
  {
    "Name": "Jajaroon",
    "Idx": 37,
    "Id": 16994341,
    "ZoneId": 53,
    "ConvertedZoneNames": [],
    "ConvertedZoneType": ""
  },
  {
    "Name": "Jijiroon",
    "Idx": 38,
    "Id": 16994342,
    "ZoneId": 53,
    "ConvertedZoneNames": [],
    "ConvertedZoneType": ""
  },
  {
    "Name": "Viviroon",
    "Idx": 39,
    "Id": 16994343,
    "ZoneId": 53,
    "ConvertedZoneNames": [],
    "ConvertedZoneType": ""
  },
  {
    "Name": "Yoyoroon",
    "Idx": 40,
    "Id": 16994344,
    "ZoneId": 53,
    "ConvertedZoneNames": [],
    "ConvertedZoneType": ""
  },
  {
    "Name": "Tsetseroon",
    "Idx": 41,
    "Id": 16994345,
    "ZoneId": 53,
    "ConvertedZoneNames": [],
    "ConvertedZoneType": ""
  },
  {
    "Name": "Mamaroon",
    "Idx": 42,
    "Id": 16994346,
    "ZoneId": 53,
    "ConvertedZoneNames": [],
    "ConvertedZoneType": ""
  },
  {
    "Name": "Mimiroon",
    "Idx": 43,
    "Id": 16994347,
    "ZoneId": 53,
    "ConvertedZoneNames": [],
    "ConvertedZoneType": ""
  },
  {
    "Name": "Pipiroon",
    "Idx": 44,
    "Id": 16994348,
    "ZoneId": 53,
    "ConvertedZoneNames": [],
    "ConvertedZoneType": ""
  },
  {
    "Name": "Poporoon",
    "Idx": 45,
    "Id": 16994349,
    "ZoneId": 53,
    "ConvertedZoneNames": [],
    "ConvertedZoneType": ""
  },
  {
    "Name": "Wata Khamazom",
    "Idx": 46,
    "Id": 16994350,
    "ZoneId": 53,
    "ConvertedZoneNames": [],
    "ConvertedZoneType": ""
  },
  {
    "Name": "Guhyun",
    "Idx": 47,
    "Id": 16994351,
    "ZoneId": 53,
    "ConvertedZoneNames": [],
    "ConvertedZoneType": ""
  },
  {
    "Name": "Wafeeyah",
    "Idx": 48,
    "Id": 16994352,
    "ZoneId": 53,
    "ConvertedZoneNames": [],
    "ConvertedZoneType": ""
  },
  {
    "Name": "Fhe Maksojha",
    "Idx": 49,
    "Id": 16994353,
    "ZoneId": 53,
    "ConvertedZoneNames": [],
    "ConvertedZoneType": ""
  },
  {
    "Name": "Buburoon",
    "Idx": 50,
    "Id": 16994354,
    "ZoneId": 53,
    "ConvertedZoneNames": [],
    "ConvertedZoneType": ""
  },
  {
    "Name": "Zazaroon",
    "Idx": 51,
    "Id": 16994355,
    "ZoneId": 53,
    "ConvertedZoneNames": [],
    "ConvertedZoneType": ""
  },
  {
    "Name": "Nadeeha",
    "Idx": 52,
    "Id": 16994356,
    "ZoneId": 53,
    "ConvertedZoneNames": [],
    "ConvertedZoneType": ""
  },
  {
    "Name": "Mumuroon",
    "Idx": 53,
    "Id": 16994357,
    "ZoneId": 53,
    "ConvertedZoneNames": [],
    "ConvertedZoneType": ""
  },
  {
    "Name": "Kyokyoroon",
    "Idx": 54,
    "Id": 16994358,
    "ZoneId": 53,
    "ConvertedZoneNames": [],
    "ConvertedZoneType": ""
  },
  {
    "Name": "Leleroon",
    "Idx": 55,
    "Id": 16994359,
    "ZoneId": 53,
    "ConvertedZoneNames": [],
    "ConvertedZoneType": ""
  },
  {
    "Name": "Yuyuroon",
    "Idx": 56,
    "Id": 16994360,
    "ZoneId": 53,
    "ConvertedZoneNames": [],
    "ConvertedZoneType": ""
  },
  {
    "Name": "Chuchuroon",
    "Idx": 57,
    "Id": 16994361,
    "ZoneId": 53,
    "ConvertedZoneNames": [],
    "ConvertedZoneType": ""
  },
  {
    "Name": "Tsotsoroon",
    "Idx": 58,
    "Id": 16994362,
    "ZoneId": 53,
    "ConvertedZoneNames": [],
    "ConvertedZoneType": ""
  },
  {
    "Name": "Sisiroon",
    "Idx": 59,
    "Id": 16994363,
    "ZoneId": 53,
    "ConvertedZoneNames": [],
    "ConvertedZoneType": ""
  },
  {
    "Name": "Loloroon",
    "Idx": 60,
    "Id": 16994364,
    "ZoneId": 53,
    "ConvertedZoneNames": [],
    "ConvertedZoneType": ""
  },
  {
    "Name": "Tataroon",
    "Idx": 61,
    "Id": 16994365,
    "ZoneId": 53,
    "ConvertedZoneNames": [],
    "ConvertedZoneType": ""
  },
  {
    "Name": "Jojoroon",
    "Idx": 62,
    "Id": 16994366,
    "ZoneId": 53,
    "ConvertedZoneNames": [],
    "ConvertedZoneType": ""
  },
  {
    "Name": "Memeroon",
    "Idx": 63,
    "Id": 16994367,
    "ZoneId": 53,
    "ConvertedZoneNames": [],
    "ConvertedZoneType": ""
  },
  {
    "Name": "",
    "Idx": 64,
    "Id": 16994368,
    "ZoneId": 53,
    "ConvertedZoneNames": [],
    "ConvertedZoneType": ""
  },
  {
    "Name": "",
    "Idx": 65,
    "Id": 16994369,
    "ZoneId": 53,
    "ConvertedZoneNames": [],
    "ConvertedZoneType": ""
  },
  {
    "Name": "Tsutsuroon",
    "Idx": 66,
    "Id": 16994370,
    "ZoneId": 53,
    "ConvertedZoneNames": [],
    "ConvertedZoneType": ""
  },
  {
    "Name": "Habadim",
    "Idx": 67,
    "Id": 16994371,
    "ZoneId": 53,
    "ConvertedZoneNames": [],
    "ConvertedZoneType": ""
  },
  {
    "Name": "Pyopyoroon",
    "Idx": 68,
    "Id": 16994372,
    "ZoneId": 53,
    "ConvertedZoneNames": [],
    "ConvertedZoneType": ""
  },
  {
    "Name": "Chichiroon",
    "Idx": 69,
    "Id": 16994373,
    "ZoneId": 53,
    "ConvertedZoneNames": [],
    "ConvertedZoneType": ""
  },
  {
    "Name": "Rararoon",
    "Idx": 70,
    "Id": 16994374,
    "ZoneId": 53,
    "ConvertedZoneNames": [],
    "ConvertedZoneType": ""
  },
  {
    "Name": "Momoroon",
    "Idx": 71,
    "Id": 16994375,
    "ZoneId": 53,
    "ConvertedZoneNames": [],
    "ConvertedZoneType": ""
  },
  {
    "Name": "Pupuroon",
    "Idx": 72,
    "Id": 16994376,
    "ZoneId": 53,
    "ConvertedZoneNames": [],
    "ConvertedZoneType": ""
  },
  {
    "Name": "Nanaroon",
    "Idx": 73,
    "Id": 16994377,
    "ZoneId": 53,
    "ConvertedZoneNames": [],
    "ConvertedZoneType": ""
  },
  {
    "Name": "Neneroon",
    "Idx": 74,
    "Id": 16994378,
    "ZoneId": 53,
    "ConvertedZoneNames": [],
    "ConvertedZoneType": ""
  },
  {
    "Name": "Nomad Moogle",
    "Idx": 75,
    "Id": 16994379,
    "ZoneId": 53,
    "ConvertedZoneNames": [],
    "ConvertedZoneType": ""
  },
  {
    "Name": "Nomad Moogle",
    "Idx": 76,
    "Id": 16994380,
    "ZoneId": 53,
    "ConvertedZoneNames": [],
    "ConvertedZoneType": ""
  },
  {
    "Name": "Awaheen",
    "Idx": 77,
    "Id": 16994381,
    "ZoneId": 53,
    "ConvertedZoneNames": [],
    "ConvertedZoneType": ""
  },
  {
    "Name": "Ququroon",
    "Idx": 78,
    "Id": 16994382,
    "ZoneId": 53,
    "ConvertedZoneNames": [],
    "ConvertedZoneType": ""
  },
  {
    "Name": "Yadhiwa",
    "Idx": 79,
    "Id": 16994383,
    "ZoneId": 53,
    "ConvertedZoneNames": [],
    "ConvertedZoneType": ""
  },
  {
    "Name": "Totoroon",
    "Idx": 80,
    "Id": 16994384,
    "ZoneId": 53,
    "ConvertedZoneNames": [],
    "ConvertedZoneType": ""
  },
  {
    "Name": "Gehuha",
    "Idx": 81,
    "Id": 16994385,
    "ZoneId": 53,
    "ConvertedZoneNames": [],
    "ConvertedZoneType": ""
  },
  {
    "Name": "???",
    "Idx": 82,
    "Id": 16994386,
    "ZoneId": 53,
    "ConvertedZoneNames": [],
    "ConvertedZoneType": ""
  },
  {
    "Name": "",
    "Idx": 83,
    "Id": 16994387,
    "ZoneId": 53,
    "ConvertedZoneNames": [],
    "ConvertedZoneType": ""
  },
  {
    "Name": "",
    "Idx": 84,
    "Id": 16994388,
    "ZoneId": 53,
    "ConvertedZoneNames": [],
    "ConvertedZoneType": ""
  },
  {
    "Name": "Gessho",
    "Idx": 85,
    "Id": 16994389,
    "ZoneId": 53,
    "ConvertedZoneNames": [],
    "ConvertedZoneType": ""
  },
  {
    "Name": "",
    "Idx": 86,
    "Id": 16994390,
    "ZoneId": 53,
    "ConvertedZoneNames": [],
    "ConvertedZoneType": ""
  },
  {
    "Name": "",
    "Idx": 87,
    "Id": 16994391,
    "ZoneId": 53,
    "ConvertedZoneNames": [],
    "ConvertedZoneType": ""
  },
  {
    "Name": "",
    "Idx": 88,
    "Id": 16994392,
    "ZoneId": 53,
    "ConvertedZoneNames": [],
    "ConvertedZoneType": ""
  },
  {
    "Name": "",
    "Idx": 89,
    "Id": 16994393,
    "ZoneId": 53,
    "ConvertedZoneNames": [],
    "ConvertedZoneType": ""
  },
  {
    "Name": "",
    "Idx": 90,
    "Id": 16994394,
    "ZoneId": 53,
    "ConvertedZoneNames": [],
    "ConvertedZoneType": ""
  },
  {
    "Name": "",
    "Idx": 91,
    "Id": 16994395,
    "ZoneId": 53,
    "ConvertedZoneNames": [],
    "ConvertedZoneType": ""
  },
  {
    "Name": "",
    "Idx": 92,
    "Id": 16994396,
    "ZoneId": 53,
    "ConvertedZoneNames": [],
    "ConvertedZoneType": ""
  },
  {
    "Name": "Kilusha",
    "Idx": 93,
    "Id": 16994397,
    "ZoneId": 53,
    "ConvertedZoneNames": [],
    "ConvertedZoneType": ""
  },
  {
    "Name": "Paparoon",
    "Idx": 94,
    "Id": 16994398,
    "ZoneId": 53,
    "ConvertedZoneNames": [],
    "ConvertedZoneType": ""
  },
  {
    "Name": "???",
    "Idx": 95,
    "Id": 16994399,
    "ZoneId": 53,
    "ConvertedZoneNames": [],
    "ConvertedZoneType": ""
  },
  {
    "Name": "",
    "Idx": 96,
    "Id": 16994400,
    "ZoneId": 53,
    "ConvertedZoneNames": [],
    "ConvertedZoneType": ""
  },
  {
    "Name": "Liliroon",
    "Idx": 97,
    "Id": 16994401,
    "ZoneId": 53,
    "ConvertedZoneNames": [],
    "ConvertedZoneType": ""
  },
  {
    "Name": "",
    "Idx": 98,
    "Id": 16994402,
    "ZoneId": 53,
    "ConvertedZoneNames": [],
    "ConvertedZoneType": ""
  },
  {
    "Name": "???",
    "Idx": 99,
    "Id": 16994403,
    "ZoneId": 53,
    "ConvertedZoneNames": [],
    "ConvertedZoneType": ""
  },
  {
    "Name": "Jayahan",
    "Idx": 100,
    "Id": 16994404,
    "ZoneId": 53,
    "ConvertedZoneNames": [],
    "ConvertedZoneType": ""
  },
  {
    "Name": "Yoyoroon",
    "Idx": 101,
    "Id": 16994405,
    "ZoneId": 53,
    "ConvertedZoneNames": [],
    "ConvertedZoneType": ""
  },
  {
    "Name": "Tsetseroon",
    "Idx": 102,
    "Id": 16994406,
    "ZoneId": 53,
    "ConvertedZoneNames": [],
    "ConvertedZoneType": ""
  },
  {
    "Name": "",
    "Idx": 103,
    "Id": 16994407,
    "ZoneId": 53,
    "ConvertedZoneNames": [],
    "ConvertedZoneType": ""
  },
  {
    "Name": "",
    "Idx": 104,
    "Id": 16994408,
    "ZoneId": 53,
    "ConvertedZoneNames": [],
    "ConvertedZoneType": ""
  },
  {
    "Name": "",
    "Idx": 105,
    "Id": 16994409,
    "ZoneId": 53,
    "ConvertedZoneNames": [],
    "ConvertedZoneType": ""
  },
  {
    "Name": "Nabihwah",
    "Idx": 106,
    "Id": 16994410,
    "ZoneId": 53,
    "ConvertedZoneNames": [],
    "ConvertedZoneType": ""
  },
  {
    "Name": "",
    "Idx": 107,
    "Id": 16994411,
    "ZoneId": 53,
    "ConvertedZoneNames": [],
    "ConvertedZoneType": ""
  },
  {
    "Name": "Dnegan",
    "Idx": 108,
    "Id": 16994412,
    "ZoneId": 53,
    "ConvertedZoneNames": [],
    "ConvertedZoneType": ""
  },
  {
    "Name": "Yafahb",
    "Idx": 109,
    "Id": 16994413,
    "ZoneId": 53,
    "ConvertedZoneNames": [],
    "ConvertedZoneType": ""
  },
  {
    "Name": "Automaton",
    "Idx": 110,
    "Id": 16994414,
    "ZoneId": 53,
    "ConvertedZoneNames": [],
    "ConvertedZoneType": ""
  },
  {
    "Name": "Elisabeth",
    "Idx": 111,
    "Id": 16994415,
    "ZoneId": 53,
    "ConvertedZoneNames": [],
    "ConvertedZoneType": ""
  },
  {
    "Name": "Iruki-Waraki",
    "Idx": 112,
    "Id": 16994416,
    "ZoneId": 53,
    "ConvertedZoneNames": [],
    "ConvertedZoneType": ""
  },
  {
    "Name": "",
    "Idx": 113,
    "Id": 16994417,
    "ZoneId": 53,
    "ConvertedZoneNames": [],
    "ConvertedZoneType": ""
  },
  {
    "Name": "",
    "Idx": 114,
    "Id": 16994418,
    "ZoneId": 53,
    "ConvertedZoneNames": [],
    "ConvertedZoneType": ""
  },
  {
    "Name": "Wadayra",
    "Idx": 115,
    "Id": 16994419,
    "ZoneId": 53,
    "ConvertedZoneNames": [],
    "ConvertedZoneType": ""
  },
  {
    "Name": "Ahgdeen",
    "Idx": 116,
    "Id": 16994420,
    "ZoneId": 53,
    "ConvertedZoneNames": [],
    "ConvertedZoneType": ""
  },
  {
    "Name": "Basweema",
    "Idx": 117,
    "Id": 16994421,
    "ZoneId": 53,
    "ConvertedZoneNames": [],
    "ConvertedZoneType": ""
  },
  {
    "Name": "lamia",
    "Idx": 118,
    "Id": 16994422,
    "ZoneId": 53,
    "ConvertedZoneNames": [],
    "ConvertedZoneType": ""
  },
  {
    "Name": "",
    "Idx": 119,
    "Id": 16994423,
    "ZoneId": 53,
    "ConvertedZoneNames": [],
    "ConvertedZoneType": ""
  },
  {
    "Name": "Galiwao",
    "Idx": 120,
    "Id": 16994424,
    "ZoneId": 53,
    "ConvertedZoneNames": [],
    "ConvertedZoneType": ""
  },
  {
    "Name": "Kobdyu",
    "Idx": 121,
    "Id": 16994425,
    "ZoneId": 53,
    "ConvertedZoneNames": [],
    "ConvertedZoneType": ""
  },
  {
    "Name": "Deminza",
    "Idx": 122,
    "Id": 16994426,
    "ZoneId": 53,
    "ConvertedZoneNames": [],
    "ConvertedZoneType": ""
  },
  {
    "Name": "Halshaob",
    "Idx": 123,
    "Id": 16994427,
    "ZoneId": 53,
    "ConvertedZoneNames": [],
    "ConvertedZoneType": ""
  },
  {
    "Name": "Game Table",
    "Idx": 124,
    "Id": 16994428,
    "ZoneId": 53,
    "ConvertedZoneNames": [],
    "ConvertedZoneType": ""
  },
  {
    "Name": "",
    "Idx": 125,
    "Id": 16994429,
    "ZoneId": 53,
    "ConvertedZoneNames": [],
    "ConvertedZoneType": ""
  },
  {
    "Name": "Kakkaroon",
    "Idx": 126,
    "Id": 16994430,
    "ZoneId": 53,
    "ConvertedZoneNames": [],
    "ConvertedZoneType": ""
  },
  {
    "Name": "Rapipi",
    "Idx": 127,
    "Id": 16994431,
    "ZoneId": 53,
    "ConvertedZoneNames": [],
    "ConvertedZoneType": ""
  },
  {
    "Name": "Eohoh",
    "Idx": 128,
    "Id": 16994432,
    "ZoneId": 53,
    "ConvertedZoneNames": [],
    "ConvertedZoneType": ""
  },
  {
    "Name": "Rutta-Watta",
    "Idx": 129,
    "Id": 16994433,
    "ZoneId": 53,
    "ConvertedZoneNames": [],
    "ConvertedZoneType": ""
  },
  {
    "Name": "Kakkarroon2",
    "Idx": 130,
    "Id": 16994434,
    "ZoneId": 53,
    "ConvertedZoneNames": [],
    "ConvertedZoneType": ""
  },
  {
    "Name": "Hunt Registry",
    "Idx": 131,
    "Id": 16994435,
    "ZoneId": 53,
    "ConvertedZoneNames": [],
    "ConvertedZoneType": ""
  },
  {
    "Name": "Porter Moogle",
    "Idx": 132,
    "Id": 16994436,
    "ZoneId": 53,
    "ConvertedZoneNames": [],
    "ConvertedZoneType": ""
  },
  {
    "Name": "Voidwatch Purveyor",
    "Idx": 134,
    "Id": 16994438,
    "ZoneId": 53,
    "ConvertedZoneNames": [],
    "ConvertedZoneType": ""
  },
  {
    "Name": "Achieve Master",
    "Idx": 135,
    "Id": 16994439,
    "ZoneId": 53,
    "ConvertedZoneNames": [],
    "ConvertedZoneType": ""
  },
  {
    "Name": "Unity Master",
    "Idx": 136,
    "Id": 16994440,
    "ZoneId": 53,
    "ConvertedZoneNames": [],
    "ConvertedZoneType": ""
  },
  {
    "Name": "Survival Guide",
    "Idx": 137,
    "Id": 16994441,
    "ZoneId": 53,
    "ConvertedZoneNames": [],
    "ConvertedZoneType": ""
  }
]